Metadata-Version: 1.0
Name: bounce-email
Version: 0.0.3
Summary: Port of Ruby version bounce_email to Python to detect bounced emails
Home-page: http://github.com/ronbeltran/bounce_email
Author: Ronnie Beltran
Author-email: rbbeltran.09@gmail.com
License: MIT
Keywords: gmail detect bounce email
Platform: UNKNOWN
